qsofinstr/CLI.py
qsofinstr/__init__.py
qsofinstr/hardware_specification.py
qsofinstr/qc_configure.py
qsofinstr/quantumcircuit.py
qsofinstr/timeslice.py
qsofinstr/IR/__init__.py
qsofinstr/IR/QASM2/__init__.py
qsofinstr/IR/QASM2/qasm2_parser.py
qsofinstr/IR/QASM2/qasm2_token.py
qsofinstr/InstructionGenerator/__init__.py
qsofinstr/InstructionGenerator/instruction.py
qsofinstr/InstructionGenerator/measurement.py
qsofinstr-0.0.1.dist-info/METADATA
qsofinstr-0.0.1.dist-info/WHEEL
qsofinstr-0.0.1.dist-info/entry_points.txt
qsofinstr-0.0.1.dist-info/top_level.txt
qsofinstr-0.0.1.dist-info/RECORD
